django_custom_app_creator/__init__.py
django_custom_app_creator/cli.py
django_custom_app_creator/management/__init__.py
django_custom_app_creator/management/commands/__init__.py
django_custom_app_creator/management/commands/startcustomapp.py
custom_app_creator-0.1.dist-info/LICENCE
custom_app_creator-0.1.dist-info/METADATA
custom_app_creator-0.1.dist-info/WHEEL
custom_app_creator-0.1.dist-info/entry_points.txt
custom_app_creator-0.1.dist-info/top_level.txt
custom_app_creator-0.1.dist-info/RECORD
