Metadata-Version: 2.1
Name: custom-app-creator
Version: 0.1
Summary: Un package Django pour créer rapidement des applications personnalisées.
Home-page: UNKNOWN
Author: AutoGen
Author-email: autogen@example.com
License: UNKNOWN
Platform: UNKNOWN
Classifier: Framework :: Django
Classifier: Programming Language :: Python
License-File: LICENCE
Requires-Dist: Django (>=3.0)
